<?xml version="1.0" encoding="UTF-8"?>

<!DOCTYPE display PUBLIC "-//Liferay//DTD Display 4.0.0//EN" "http://www.liferay.com/dtd/liferay-display_4_0_0.dtd">

<!-- Generated by OpenXava: Wed Nov 12 22:31:32 CET 2014 --> 
<display>
	<category name="category.Document"> 
		<portlet id="DocumentRelationship" /> 
		<portlet id="Description" /> 
		<portlet id="Document" /> 
		<portlet id="DocumentId" /> 
		<portlet id="KeyWord" /> 
		<portlet id="PostalAddress" /> 
		<portlet id="Title" /> 
		<portlet id="TownDetail" /> 
		<portlet id="Summary" /> 
		<portlet id="ElectronicAddress" /> 
		<portlet id="TelephoneNumber" /> 
		<portlet id="DocumentClassification" /> 
		<portlet id="StreetDetail" /> 
		<portlet id="DocumentRevision" /> 
		<portlet id="Person" />
   
	</category>
</display>